lambida/__init__.py
lambida/datazone/DataZone.py
lambida/datazone/RawData.py
lambida/datazone/TransientData.py
lambida/datazone/__init__.py
lambida/datazone/datazone.py
lambida/datazone/rawdata.py
lambida/datazone/transientdata.py
lambida/datazone/utils.py
lambida/utils/__init__.py
lambida/utils/lambda_log.py
lambida/utils/s3_upload_client.py
lambida-0.2.25.dist-info/DESCRIPTION.rst
lambida-0.2.25.dist-info/METADATA
lambida-0.2.25.dist-info/RECORD
lambida-0.2.25.dist-info/WHEEL
lambida-0.2.25.dist-info/metadata.json
lambida-0.2.25.dist-info/top_level.txt
