Metadata-Version: 2.0
Name: lambida
Version: 0.2.25
Summary: An AWS utility package
Home-page: UNKNOWN
Author: AMARO
Author-email: data@amaro.com
License: UNKNOWN
Platform: UNKNOWN
Classifier: Programming Language :: Python :: 3
Classifier: License :: OSI Approved :: MIT License
Classifier: Operating System :: OS Independent
Requires-Dist: boto3 (==1.9.112)
Requires-Dist: botocore (==1.12.112)
Requires-Dist: s3transfer (==0.2.0)
Requires-Dist: jmespath (==0.9.4)
Requires-Dist: docutils (==0.14)
Requires-Dist: urllib3 (==1.24.1)
Requires-Dist: python-dateutil (==2.8.0)
Requires-Dist: six (==1.12.0)
